omkar_periodic_table-0.1.dist-info/DESCRIPTION.rst
omkar_periodic_table-0.1.dist-info/METADATA
omkar_periodic_table-0.1.dist-info/RECORD
omkar_periodic_table-0.1.dist-info/WHEEL
omkar_periodic_table-0.1.dist-info/metadata.json
omkar_periodic_table-0.1.dist-info/top_level.txt
periodic_table/__init.py
periodic_table/ptable.py
