Metadata-Version: 2.0
Name: omkar-periodic-table
Version: 0.1
Summary: chemistry symbols and name
Home-page: UNKNOWN
Author: omkar
Author-email: xyz@test.com
License: MIT
Platform: UNKNOWN
